README.md
setup.cfg
setup.py
py_json_serialize/__init__.py
py_json_serialize.egg-info/PKG-INFO
py_json_serialize.egg-info/SOURCES.txt
py_json_serialize.egg-info/dependency_links.txt
py_json_serialize.egg-info/top_level.txt