Metadata-Version: 2.1
Name: py-json-serialize
Version: 0.9.0
Summary: json serialize library for Python 2 and 3
Home-page: https://github.com/randydu/py-json-serialize.git
Author: Randy Du
Author-email: randydu@gmail.com
License: MIT
Keywords: serialize,json
Platform: UNKNOWN
Classifier: Development Status :: 4 - Beta
Classifier: Intended Audience :: Developers
Classifier: Operating System :: OS Independent
Classifier: Topic :: Software Development :: Libraries
Classifier: Topic :: Software Development :: Libraries :: Python Modules
Classifier: License :: OSI Approved :: MIT License
Classifier: Programming Language :: Python :: 2
Classifier: Programming Language :: Python :: 3
